jupyter_iam/__init__.py
jupyter_iam/__main__.py
jupyter_iam/__version__.py
jupyter_iam/application.py
jupyter_iam/serverapplication.py
jupyter_iam/handlers/__init__.py
jupyter_iam/handlers/base.py
jupyter_iam/handlers/config/__init__.py
jupyter_iam/handlers/config/handler.py
jupyter_iam/handlers/index/__init__.py
jupyter_iam/handlers/index/handler.py
jupyter_iam/handlers/oauth/__init__.py
jupyter_iam/handlers/oauth/handler.py
jupyter_iam/static/README.md
jupyter_iam/templates/index.html
jupyter_iam/tests/__init__.py
jupyter_iam/tests/test_handlers.py
jupyter_iam-1.2.12.data/data/etc/jupyter/jupyter_notebook_config.d/jupyter_iam.json
jupyter_iam-1.2.12.data/data/etc/jupyter/jupyter_server_config.d/jupyter_iam.json
jupyter_iam-1.2.12.dist-info/METADATA
jupyter_iam-1.2.12.dist-info/WHEEL
jupyter_iam-1.2.12.dist-info/entry_points.txt
jupyter_iam-1.2.12.dist-info/licenses/LICENSE
jupyter_iam-1.2.12.dist-info/RECORD
